strupnet/__init__.py
strupnet/snn.py
strupnet/utils.py
strupnet/vnn.py
strupnet/layers/G.py
strupnet/layers/GR.py
strupnet/layers/H.py
strupnet/layers/LA.py
strupnet/layers/P.py
strupnet/layers/R.py
strupnet/layers/RBF.py
strupnet/layers/__init__.py
strupnet/layers/force.py
strupnet/nn/__init__.py
strupnet/nn/activation.py
strupnet/nn/net.py
strupnet/nn/poly.py
strupnet/nn/scalar.py
strupnet/tests/__init__.py
strupnet/tests/test_sympnet.py
strupnet-0.0.4.dist-info/LICENSE
strupnet-0.0.4.dist-info/METADATA
strupnet-0.0.4.dist-info/WHEEL
strupnet-0.0.4.dist-info/top_level.txt
strupnet-0.0.4.dist-info/RECORD
