Metadata-Version: 2.1
Name: strupnet
Version: 0.0.4
Summary: Structure-preserving neural networks
Author-email: Ben Tapley <bentapley@hotmail.com>
License: MIT License
Project-URL: Homepage, https://github.com/bentaps/strupnet
Keywords: pytorch,neural networks,physics-informed machine learning,structure-preserving neural networks
Classifier: License :: OSI Approved :: MIT License
Classifier: Programming Language :: Python
Classifier: Programming Language :: Python :: 3
Requires-Python: >=3.9
License-File: LICENSE
Requires-Dist: torch
Provides-Extra: dev
Requires-Dist: black ; extra == 'dev'
Requires-Dist: bumpver ; extra == 'dev'
Requires-Dist: isort ; extra == 'dev'
Requires-Dist: pip-tools ; extra == 'dev'
Requires-Dist: pytest ; extra == 'dev'
